plot_me/classify.py
plot_me/reports.py
plot_me/parse_DB.py
plot_me/tools.py
plot_me/parse_multi.py
plot_me/__init__.py
plot_me/bio.py
plot_me/main.py
plot_me/cython_module/cyt_ext.c
plot_me/cython_module/cyt_ext.pyx
plot_me/cython_module/cyt_ext.cpython-38-x86_64-linux-gnu.so
plot_me/cython_module/__init__.py
PLoT_ME-0.9.1.dist-info/top_level.txt
PLoT_ME-0.9.1.dist-info/entry_points.txt
PLoT_ME-0.9.1.dist-info/WHEEL
PLoT_ME-0.9.1.dist-info/METADATA
PLoT_ME-0.9.1.dist-info/LICENSE
PLoT_ME-0.9.1.dist-info/RECORD
