Metadata-Version: 2.1
Name: PLoT-ME
Version: 0.9.1
Summary: Pre-classification of Long-reads for Memory Efficient Taxonomic assignment
Home-page: https://github.com/sylvain-ri/PLoT-ME
Author: Sylvain Riondet
Author-email: sylvainrionder@gmail.com
License: UNKNOWN
Platform: UNKNOWN
Classifier: Intended Audience :: Developers
Classifier: Intended Audience :: Healthcare Industry
Classifier: Intended Audience :: Science/Research
Classifier: License :: OSI Approved :: MIT License
Classifier: Operating System :: Unix
Classifier: Operating System :: POSIX :: Linux
Classifier: Programming Language :: Python :: 3
Classifier: Programming Language :: Python :: 3.7
Classifier: Topic :: Database
Classifier: Topic :: Scientific/Engineering
Classifier: Topic :: Scientific/Engineering :: Bio-Informatics
Requires-Python: >=3.7
Requires-Dist: biopython (>=1.72)
Requires-Dist: Cython (>=0.26.2)
Requires-Dist: ete3 (>=3.1.1)
Requires-Dist: numpy (>=1.16.5)
Requires-Dist: pandas (>=0.23)
Requires-Dist: scikit-learn (>=0.18)
Requires-Dist: setuptools (>=39.1.0)
Requires-Dist: tqdm (>=4.24.0)
